xen_tokenizer/__init__.py
xen_tokenizer/config.py
xen_tokenizer/exceptions.py
xen_tokenizer/processor.py
xen_tokenizer/tokenizer.py
xen_tokenizer/version.py
xen_tokenizer-0.1.1.dist-info/licenses/LICENSE
xen_tokenizer-0.1.1.dist-info/METADATA
xen_tokenizer-0.1.1.dist-info/WHEEL
xen_tokenizer-0.1.1.dist-info/top_level.txt
xen_tokenizer-0.1.1.dist-info/RECORD
