Metadata-Version: 2.4
Name: xen-tokenizer
Version: 0.1.1
Summary: XenArcAI's High-Performance Tokenization Library
Author-email: XenArcAI <engineering@xenarc.ai>
License-Expression: MIT
Classifier: Development Status :: 4 - Beta
Classifier: Intended Audience :: Developers
Classifier: Intended Audience :: Science/Research
Classifier: Programming Language :: Python :: 3 :: Only
Classifier: Programming Language :: Python :: 3.8
Classifier: Programming Language :: Python :: 3.9
Classifier: Programming Language :: Python :: 3.10
Classifier: Topic :: Scientific/Engineering
Classifier: Topic :: Scientific/Engineering :: Artificial Intelligence
Classifier: Topic :: Text Processing
Classifier: Topic :: Text Processing :: Linguistic
Classifier: Typing :: Typed
Requires-Python: >=3.8
License-File: LICENSE
Requires-Dist: torch<3.0.0,>=1.8.0
Requires-Dist: transformers<5.0.0,>=4.18.0
Requires-Dist: tqdm>=4.62.0
Requires-Dist: numpy>=1.20.0
Requires-Dist: filelock>=3.0.0
Provides-Extra: azure
Requires-Dist: azure-storage-blob>=12.8.1; extra == "azure"
Requires-Dist: pyarrow>=6.0.0; extra == "azure"
Requires-Dist: pandas>=1.3.0; extra == "azure"
Provides-Extra: dev
Requires-Dist: pytest>=6.0.0; extra == "dev"
Requires-Dist: pytest-cov>=2.12.0; extra == "dev"
Requires-Dist: black>=21.7b0; extra == "dev"
Requires-Dist: isort>=5.9.0; extra == "dev"
Requires-Dist: mypy>=0.910; extra == "dev"
Requires-Dist: flake8>=4.0.0; extra == "dev"
Requires-Dist: pre-commit>=2.15.0; extra == "dev"
Requires-Dist: types-PyYAML; extra == "dev"
Requires-Dist: types-requests; extra == "dev"
Dynamic: license-file
